whatstrending/__init__.py
whatstrending/whatstrending.py
whatstrending-0.2.4.dist-info/LICENSE
whatstrending-0.2.4.dist-info/METADATA
whatstrending-0.2.4.dist-info/WHEEL
whatstrending-0.2.4.dist-info/entry_points.txt
whatstrending-0.2.4.dist-info/top_level.txt
whatstrending-0.2.4.dist-info/RECORD
