Metadata-Version: 2.1
Name: whatstrending
Version: 0.2.4
Summary: A simple Python CLI tool using which you can see Twitter Top trends of any country in your Terminal.
Home-page: https://github.com/iamtalhaasghar/whats-trending
Author: Talha Asghar
Author-email: talhaasghar.contact@simplelogin.fr
License: UNKNOWN
Platform: UNKNOWN
Classifier: Programming Language :: Python :: 3
Classifier: License :: OSI Approved :: GNU General Public License v3 (GPLv3)
Classifier: Operating System :: OS Independent
Requires-Python: >=3.6
License-File: LICENSE
Requires-Dist: beautifulsoup4
Requires-Dist: lxml
Requires-Dist: requests
Requires-Dist: selenium
